ghapi/__init__.py
ghapi/_modidx.py
ghapi/_nbdev.py
ghapi/actions.py
ghapi/all.py
ghapi/auth.py
ghapi/build_lib.py
ghapi/cli.py
ghapi/core.py
ghapi/event.py
ghapi/metadata.py
ghapi/page.py
ghapi/templates.py
ghapi-1.0.7.dist-info/licenses/LICENSE
ghapi-1.0.7.dist-info/METADATA
ghapi-1.0.7.dist-info/WHEEL
ghapi-1.0.7.dist-info/entry_points.txt
ghapi-1.0.7.dist-info/top_level.txt
ghapi-1.0.7.dist-info/RECORD
