Metadata-Version: 2.4
Name: ghapi
Version: 1.0.7
Summary: A python client for the GitHub API
Home-page: https://github.com/fastai/ghapi
Author: Jeremy Howard
Author-email: info@fast.ai
License: Apache Software License 2.0
Project-URL: Documentation, https://ghapi.fast.ai/
Keywords: github api
Classifier: Development Status :: 6 - Mature
Classifier: Intended Audience :: Developers
Classifier: License :: OSI Approved :: Apache Software License
Classifier: Natural Language :: English
Classifier: Programming Language :: Python :: 3.7
Classifier: Programming Language :: Python :: 3.8
Classifier: Programming Language :: Python :: 3.9
Classifier: Programming Language :: Python :: 3.10
Classifier: Programming Language :: Python :: 3.11
Classifier: Programming Language :: Python :: 3.12
Requires-Python: >=3.7
License-File: LICENSE
Requires-Dist: packaging
Requires-Dist: fastcore>=1.7.2
Provides-Extra: dev
Requires-Dist: jsonref; extra == "dev"
Requires-Dist: matplotlib; extra == "dev"
Requires-Dist: nbclassic; extra == "dev"
Requires-Dist: nbdev; extra == "dev"
Requires-Dist: pysymbol_llm; extra == "dev"
Requires-Dist: llms-txt; extra == "dev"
Dynamic: author
Dynamic: author-email
Dynamic: classifier
Dynamic: description
Dynamic: description-content-type
Dynamic: home-page
Dynamic: keywords
Dynamic: license
Dynamic: license-file
Dynamic: project-url
Dynamic: provides-extra
Dynamic: requires-dist
Dynamic: requires-python
Dynamic: summary
